promptflow/__init__.py
promptflow/_version.py
promptflow-1.18.2.data/scripts/pf.autocomplete.sh
promptflow-1.18.2.dist-info/licenses/NOTICE.txt
promptflow-1.18.2.dist-info/METADATA
promptflow-1.18.2.dist-info/WHEEL
promptflow-1.18.2.dist-info/top_level.txt
promptflow-1.18.2.dist-info/RECORD
