Metadata-Version: 2.4
Name: promptflow
Version: 1.18.2
Summary: Prompt flow Python SDK - build high-quality LLM apps
Home-page: https://github.com/microsoft/promptflow
Author: Microsoft Corporation
Author-email: aml-pt-eng@microsoft.com
License: MIT License
Project-URL: Bug Reports, https://github.com/microsoft/promptflow/issues
Project-URL: Source, https://github.com/microsoft/promptflow
Classifier: Programming Language :: Python
Classifier: Programming Language :: Python :: 3
Classifier: Programming Language :: Python :: 3 :: Only
Classifier: Programming Language :: Python :: 3.9
Classifier: Programming Language :: Python :: 3.10
Classifier: Programming Language :: Python :: 3.11
Classifier: License :: OSI Approved :: MIT License
Classifier: Operating System :: OS Independent
Requires-Python: <4.0,>=3.9
License-File: NOTICE.txt
Requires-Dist: promptflow-tracing==1.18.2
Requires-Dist: promptflow-core==1.18.2
Requires-Dist: promptflow-devkit==1.18.2
Provides-Extra: all
Requires-Dist: promptflow-core[executor-service]==1.18.2; extra == "all"
Requires-Dist: promptflow-devkit[all]==1.18.2; extra == "all"
Requires-Dist: promptflow-azure==1.18.2; extra == "all"
Provides-Extra: azure
Requires-Dist: promptflow-azure==1.18.2; extra == "azure"
Provides-Extra: executable
Requires-Dist: promptflow-devkit[executable]==1.18.2; extra == "executable"
Provides-Extra: azureml-serving
Requires-Dist: promptflow-core[azureml-serving]==1.18.2; extra == "azureml-serving"
Provides-Extra: executor-service
Requires-Dist: promptflow-core[executor-service]==1.18.2; extra == "executor-service"
Dynamic: author
Dynamic: author-email
Dynamic: classifier
Dynamic: description
Dynamic: description-content-type
Dynamic: home-page
Dynamic: license
Dynamic: license-file
Dynamic: project-url
Dynamic: provides-extra
Dynamic: requires-dist
Dynamic: requires-python
Dynamic: summary
